{
  "Revenant": {
    "I": 500,
    "II": 20000,
    "III": 400000,
    "IV": 1500000,
    "V": 10000000
  },
  "Tarantula": {
    "I": 750,
    "II": 30000,
    "III": 900000,
    "IV": 2400000
  },
  "Sven": {
    "I": 2000,
    "II": 40000,
    "III": 750000,
    "IV": 2000000
  },
  "Voidgloom": {
    "I": 300000,
    "II": 12000000,
    "III": 50000000,
    "IV": 210000000
  },
  "Inferno": {
    "I": 2500000,
    "II": 10000000,
    "III": 45000000,
    "IV": 150000000
  },
  "Riftstalker": {
    "I": 625,
    "II": 1100,
    "III": 1800,
    "IV": 2400,
    "V": 3000
  }
}
